zelfred/__init__.py
zelfred/_version.py
zelfred/action.py
zelfred/api.py
zelfred/constants.py
zelfred/debug.py
zelfred/dropdown.py
zelfred/events.py
zelfred/exc.py
zelfred/item.py
zelfred/keyboard.py
zelfred/line_editor.py
zelfred/paths.py
zelfred/query.py
zelfred/render.py
zelfred/ui.py
zelfred/ui_formatter.py
zelfred/ui_process_key_pressed.py
zelfred/docs/__init__.py
zelfred/gallery/__init__.py
zelfred/gallery/e01_random_password_generator.py
zelfred/gallery/e02_calculate_file_checksum.py
zelfred/gallery/e03_select_item_using_fuzzy_match.py
zelfred/gallery/e04_google_search_with_suggestion.py
zelfred/gallery/e05_search_google_chrome_bookmark.py
zelfred/gallery/e06_folder_and_file_search.py
zelfred/gallery/e07_password_book.py
zelfred/gallery/e08_refresh_cache_v1.py
zelfred/gallery/e09_refresh_cache_v2.py
zelfred/gallery/e10_json_formatter.py
zelfred/gallery/e10_refresh_cache_v3.py
zelfred/gallery/e11_json_formatter.py
zelfred/tests/__init__.py
zelfred/tests/helper.py
zelfred/vendor/__init__.py
zelfred/vendor/os_platform.py
zelfred/vendor/pytest_cov_helper.py
zelfred-0.4.1.dist-info/AUTHORS.rst
zelfred-0.4.1.dist-info/LICENSE.txt
zelfred-0.4.1.dist-info/METADATA
zelfred-0.4.1.dist-info/WHEEL
zelfred-0.4.1.dist-info/top_level.txt
zelfred-0.4.1.dist-info/RECORD
